odoo/addons/stock_location_position/README.rst
odoo/addons/stock_location_position/__init__.py
odoo/addons/stock_location_position/__manifest__.py
odoo/addons/stock_location_position/i18n/it.po
odoo/addons/stock_location_position/i18n/stock_location_position.pot
odoo/addons/stock_location_position/models/__init__.py
odoo/addons/stock_location_position/models/stock_location.py
odoo/addons/stock_location_position/readme/CONTRIBUTORS.rst
odoo/addons/stock_location_position/readme/CREDITS.rst
odoo/addons/stock_location_position/readme/DESCRIPTION.rst
odoo/addons/stock_location_position/static/description/icon.png
odoo/addons/stock_location_position/static/description/index.html
odoo/addons/stock_location_position/views/stock_location.xml
odoo14_addon_stock_location_position-14.0.1.0.1.dev5.dist-info/METADATA
odoo14_addon_stock_location_position-14.0.1.0.1.dev5.dist-info/WHEEL
odoo14_addon_stock_location_position-14.0.1.0.1.dev5.dist-info/top_level.txt
odoo14_addon_stock_location_position-14.0.1.0.1.dev5.dist-info/RECORD
